statistics_probability_curve_pb123/__init__.py
statistics_probability_curve_pb123/norm_curve.py
statistics_probability_curve_pb123-0.0.1.dist-info/LICENSE.txt
statistics_probability_curve_pb123-0.0.1.dist-info/METADATA
statistics_probability_curve_pb123-0.0.1.dist-info/WHEEL
statistics_probability_curve_pb123-0.0.1.dist-info/top_level.txt
statistics_probability_curve_pb123-0.0.1.dist-info/RECORD
